blockbuster/core/__init__.py
blockbuster/core/factory.py
blockbuster/core/io.py
blockbuster/core/model.py
blockbuster_core-0.1.4.dist-info/WHEEL
blockbuster_core-0.1.4.dist-info/METADATA
blockbuster_core-0.1.4.dist-info/RECORD
