Metadata-Version: 2.1
Name: blockbuster-core
Version: 0.1.4
Summary: 
Home-page: UNKNOWN
License: GPL-3.0
Author: Owen Campbell
Requires-Python: >=3.6
Classifier: License :: OSI Approved :: GNU General Public License v3 (GPLv3)
Classifier: Programming Language :: Python :: 3
Classifier: Programming Language :: Python :: 3.6
Classifier: Programming Language :: Python :: 3.7
Requires-Dist: marshmallow (>=2.18,<3.0)
